{
    "day": 0,
    "letters": [
        "e",
        "j",
        "z",
        "d",
        "t",
        "i"
    ],
    "center": "r",
    "max_score": 1282,
    "n_words": 192,
    "n_pangrams": 1,
    "words": [
        "riziere",
        "triee",
        "deterrez",
        "redit",
        "reeditiez",
        "detirerez",
        "eteterez",
        "tiret",
        "territ",
        "titrez",
        "detiree",
        "terriere",
        "editer",
        "tirer",
        "dire",
        "rizerie",
        "irritiez",
        "reiterer",
        "tire",
        "dedier",
        "terrer",
        "etirez",
        "tirez",
        "irritee",
        "ririez",
        "detire",
        "titriez",
        "tetiere",
        "triiez",
        "etirerez",
        "reitererez",
        "rejetiez",
        "retirer",
        "triere",
        "derideriez",
        "eteteriez",
        "reeditez",
        "reitre",
        "ridee",
        "ridez",
        "reiez",
        "etier",
        "deterrerez",
        "reiteriez",
        "dedirez",
        "redie",
        "rire",
        "rejetee",
        "errez",
        "deterriez",
        "rejetterez",
        "dediriez",
        "tritie",
        "rejeter",
        "errerez",
        "redite",
        "deterre",
        "terree",
        "ridiez",
        "deterreriez",
        "terrirez",
        "reitere",
        "terrier",
        "dedierez",
        "tritiee",
        "trieriez",
        "trie",
        "tertre",
        "reedite",
        "iteree",
        "reiteree",
        "irrite",
        "reerez",
        "editeriez",
        "iterer",
        "teter",
        "tiediriez",
        "terrir",
        "trierez",
        "reer",
        "deride",
        "rejette",
        "erriez",
        "detiriez",
        "trier",
        "itereriez",
        "dedire",
        "teteriez",
        "reeriez",
        "tiree",
        "iridie",
        "riez",
        "iterez",
        "triedre",
        "rediriez",
        "deridez",
        "jeter",
        "retiriez",
        "tireriez",
        "detirez",
        "zire",
        "terre",
        "tirerez",
        "etireriez",
        "dedieriez",
        "reiterez",
        "rejetteriez",
        "jetterez",
        "etire",
        "jetteriez",
        "retire",
        "deterree",
        "reez",
        "riderez",
        "etiree",
        "deterrer",
        "reediter",
        "dejeter",
        "ziride",
        "terreriez",
        "etre",
        "irriter",
        "detireriez",
        "terririez",
        "diedre",
        "itere",
        "teterez",
        "riiez",
        "treize",
        "erre",
        "irritez",
        "diriez",
        "terrerez",
        "dejetteriez",
        "etirer",
        "retirez",
        "terri",
        "jerez",
        "tiedirez",
        "deriderez",
        "direz",
        "rejetez",
        "titrerez",
        "retiree",
        "derriere",
        "titree",
        "reeditee",
        "redirez",
        "terrez",
        "tiriez",
        "eteter",
        "reediteriez",
        "titreriez",
        "ride",
        "redire",
        "rirez",
        "etiriez",
        "deridiez",
        "rideriez",
        "iriez",
        "retirerez",
        "titre",
        "deridee",
        "rider",
        "dejetterez",
        "iteriez",
        "iridee",
        "editerez",
        "erreriez",
        "retireriez",
        "terriez",
        "reediterez",
        "rizette",
        "errer",
        "rite",
        "iridiee",
        "itererez",
        "derider",
        "rejet",
        "titrer",
        "eider",
        "detirer",
        "etrier",
        "tridi",
        "reitereriez",
        "tirette",
        "irez",
        "irriterez",
        "triez",
        "rejete",
        "tiedir",
        "irriteriez"
    ],
    "pangrammes": [
        "dejetteriez"
    ]
}{
    "day": 1,
    "letters": [
        "s",
        "u",
        "t",
        "e",
        "j",
        "m"
    ],
    "center": "n",
    "max_score": 1087,
    "n_words": 173,
    "n_pangrams": 3,
    "words": [
        "mesusent",
        "neems",
        "ente",
        "menses",
        "nettes",
        "nette",
        "neem",
        "sennes",
        "stents",
        "jeun",
        "tussent",
        "justement",
        "nems",
        "mnemes",
        "menteuse",
        "tunes",
        "nemeens",
        "jutent",
        "menus",
        "tennesse",
        "nettetes",
        "tenesmes",
        "sens",
        "sement",
        "jettent",
        "sene",
        "entetes",
        "mettent",
        "juments",
        "entent",
        "nees",
        "sentes",
        "tuneuses",
        "nemeennes",
        "jeunee",
        "tunees",
        "nemes",
        "ment",
        "menees",
        "entetees",
        "senes",
        "tuent",
        "sente",
        "jeunees",
        "nets",
        "nuent",
        "etetements",
        "sustentees",
        "entente",
        "jejunums",
        "entetent",
        "entees",
        "jeuneuse",
        "teneuse",
        "stent",
        "tenements",
        "menues",
        "mesentente",
        "nenets",
        "nument",
        "jeunes",
        "muent",
        "menue",
        "senses",
        "enjeu",
        "jeunet",
        "menes",
        "nettement",
        "mesententes",
        "junte",
        "sensee",
        "sustente",
        "mense",
        "jeunesse",
        "menteuses",
        "jeunette",
        "sustentes",
        "tente",
        "jumentes",
        "etetement",
        "emmenees",
        "emmenee",
        "usent",
        "emmenent",
        "nettete",
        "nemeen",
        "entetement",
        "juntes",
        "ententes",
        "sustentee",
        "mentes",
        "unes",
        "entete",
        "mente",
        "sent",
        "eussent",
        "meneuse",
        "menu",
        "testent",
        "nenes",
        "sense",
        "neuneu",
        "tenues",
        "tetent",
        "mneme",
        "tenue",
        "mens",
        "nemeenne",
        "musent",
        "tentee",
        "tentees",
        "mussent",
        "emmenes",
        "sensement",
        "tenu",
        "etetent",
        "nenette",
        "nuement",
        "menee",
        "sensees",
        "menuets",
        "sustentent",
        "tentent",
        "mutent",
        "tune",
        "tunent",
        "entes",
        "tenement",
        "neuneus",
        "neume",
        "jeunettes",
        "usnee",
        "jument",
        "meneuses",
        "jeuneuses",
        "mene",
        "neumes",
        "tenesme",
        "nene",
        "nuees",
        "eumenes",
        "usnees",
        "nues",
        "tennesses",
        "tunee",
        "jeunement",
        "menuet",
        "menent",
        "sussent",
        "senne",
        "suent",
        "nenettes",
        "eumene",
        "teneuses",
        "entetements",
        "entetee",
        "sentent",
        "tenus",
        "emettent",
        "tentes",
        "emmene",
        "jeune",
        "jumente",
        "entee",
        "nuee",
        "mentent",
        "jejunum",
        "jeunent",
        "memement",
        "tuneuse",
        "emussent",
        "jeunesses",
        "jeunets"
    ],
    "pangrammes": [
        "justement",
        "juments",
        "jumentes"
    ]
}