{
    "day": 1033,
    "letters": [
        "o",
        "m",
        "t",
        "r",
        "c",
        "n"
    ],
    "center": "a",
    "max_score": 2416,
    "n_words": 398,
    "n_pangrams": 4,
    "words": [
        "canat",
        "rancon",
        "tonna",
        "otat",
        "anonna",
        "romancant",
        "ancra",
        "manant",
        "montrat",
        "maranta",
        "connota",
        "cocotta",
        "tatant",
        "marra",
        "toronnat",
        "anon",
        "ataman",
        "cant",
        "cana",
        "naan",
        "noma",
        "nattant",
        "cartonnat",
        "tancant",
        "contrat",
        "amorca",
        "tarant",
        "tronconna",
        "comatat",
        "actant",
        "tarat",
        "matant",
        "cotta",
        "aramon",
        "tamtam",
        "actorat",
        "nacrant",
        "maronnant",
        "canonna",
        "maton",
        "cata",
        "motta",
        "normant",
        "tatonnant",
        "montrant",
        "amman",
        "tancat",
        "nacra",
        "monta",
        "cantonnant",
        "nanar",
        "nanan",
        "carcan",
        "caraco",
        "aman",
        "cantat",
        "amant",
        "connotant",
        "manocontact",
        "manta",
        "ratant",
        "marmonnat",
        "cartant",
        "cornant",
        "taco",
        "coconnat",
        "cramat",
        "cottant",
        "ocrant",
        "tortora",
        "crottat",
        "accot",
        "arma",
        "ornant",
        "marc",
        "cranant",
        "marmottant",
        "tantra",
        "tramat",
        "nota",
        "cotant",
        "tama",
        "ramonat",
        "tartan",
        "ratat",
        "ancrat",
        "crama",
        "otant",
        "tantot",
        "cocontractant",
        "annota",
        "marron",
        "cantant",
        "tronconnant",
        "accotat",
        "norma",
        "cama",
        "tatat",
        "cartonnant",
        "marmonnant",
        "cocoonant",
        "cotonnant",
        "cantonna",
        "mata",
        "raccroc",
        "canta",
        "armant",
        "ramonant",
        "maar",
        "tatonna",
        "cartonna",
        "armat",
        "carta",
        "comata",
        "acra",
        "canna",
        "amarra",
        "canonnat",
        "maconnat",
        "canot",
        "carton",
        "montat",
        "tracat",
        "arconnat",
        "tomant",
        "monaco",
        "accotant",
        "natta",
        "tata",
        "raton",
        "trantran",
        "trocart",
        "craton",
        "cramcram",
        "ranconna",
        "racontant",
        "tacon",
        "romanca",
        "cancan",
        "matat",
        "traca",
        "ronronnat",
        "tonnat",
        "canonnant",
        "carrat",
        "tronant",
        "comma",
        "marmotta",
        "arcon",
        "contact",
        "maraca",
        "marcottant",
        "cocoonat",
        "nana",
        "camat",
        "roman",
        "trottant",
        "cartat",
        "octant",
        "tarama",
        "nattat",
        "manat",
        "tact",
        "tarmac",
        "cannant",
        "cramant",
        "canotant",
        "omra",
        "tronat",
        "nocant",
        "macro",
        "maconnant",
        "montra",
        "amorcat",
        "carra",
        "contactat",
        "arconnant",
        "marronna",
        "tonnant",
        "ocra",
        "crana",
        "canon",
        "romancat",
        "ramant",
        "coca",
        "contrarc",
        "racontat",
        "tacca",
        "romano",
        "cocottat",
        "comatant",
        "contat",
        "taratata",
        "toma",
        "contactant",
        "anona",
        "mana",
        "crantant",
        "annoncant",
        "tortorant",
        "ratonnat",
        "tarot",
        "annoncat",
        "accorant",
        "annonca",
        "marrant",
        "cotonnat",
        "carron",
        "ataca",
        "cantor",
        "narco",
        "tacot",
        "raca",
        "armon",
        "macron",
        "tracant",
        "tatonnat",
        "orant",
        "torana",
        "cotonna",
        "octa",
        "trona",
        "marnat",
        "ornat",
        "cocoona",
        "concoctant",
        "arconna",
        "marrat",
        "cota",
        "cancana",
        "annotant",
        "carrant",
        "cranat",
        "toman",
        "cranta",
        "cocotant",
        "atman",
        "rotant",
        "mamma",
        "notat",
        "crottant",
        "ronronna",
        "raconta",
        "cormoran",
        "marnant",
        "crantat",
        "tannat",
        "canotat",
        "rotat",
        "cacao",
        "amorcant",
        "tract",
        "amarrant",
        "carottant",
        "anonnat",
        "manon",
        "natron",
        "cartoon",
        "maronna",
        "cornat",
        "actat",
        "marcotta",
        "nacrat",
        "normat",
        "carottat",
        "cornac",
        "marronnant",
        "mama",
        "taro",
        "orna",
        "rama",
        "cotat",
        "connotat",
        "rata",
        "toronna",
        "mammo",
        "cannat",
        "cancanat",
        "tram",
        "ranconnat",
        "accora",
        "cottat",
        "narra",
        "tanna",
        "racoon",
        "canar",
        "narrat",
        "toccata",
        "contractat",
        "accota",
        "ranconnant",
        "marmonna",
        "arac",
        "carrom",
        "marmottat",
        "racontar",
        "antan",
        "tara",
        "taon",
        "catamaran",
        "tramant",
        "rota",
        "marcottat",
        "tatar",
        "tronconnat",
        "concocta",
        "ottoman",
        "contant",
        "rancart",
        "tractant",
        "canant",
        "nommant",
        "cocota",
        "comtat",
        "contracta",
        "accorat",
        "contractant",
        "atoca",
        "morna",
        "amarrat",
        "canton",
        "noca",
        "camorra",
        "accort",
        "mottat",
        "ratonnant",
        "mara",
        "trama",
        "acta",
        "ratonna",
        "trac",
        "nommat",
        "notant",
        "anar",
        "canara",
        "coconna",
        "nomma",
        "cantonnat",
        "marronnat",
        "carat",
        "ancrant",
        "matamata",
        "cancanant",
        "accon",
        "macon",
        "coconnant",
        "crac",
        "tonca",
        "coma",
        "cran",
        "ramat",
        "accro",
        "nacarat",
        "tomat",
        "tannant",
        "contacta",
        "corna",
        "annotat",
        "macaron",
        "cocottant",
        "cocotat",
        "nocat",
        "montant",
        "narrant",
        "marmot",
        "ramona",
        "cracra",
        "mottant",
        "conta",
        "maronnat",
        "coran",
        "trottat",
        "ocrat",
        "tracta",
        "anonnant",
        "contra",
        "maman",
        "carotta",
        "contrant",
        "trotta",
        "mantra",
        "caca",
        "tractat",
        "concoctat",
        "toronnant",
        "maconna",
        "ronronnant",
        "camant",
        "tant",
        "marna",
        "tann",
        "amont",
        "tanca",
        "canota",
        "acon",
        "accroc",
        "crotta",
        "tortorat"
    ],
    "pangrammes": [
        "romancant",
        "marcottant",
        "romancat",
        "amorcant"
    ]
}