{
    "day": 329,
    "letters": [
        "m",
        "t",
        "c",
        "l",
        "r",
        "u"
    ],
    "center": "e",
    "max_score": 1927,
    "n_words": 332,
    "n_pangrams": 1,
    "words": [
        "terme",
        "emut",
        "emuler",
        "meme",
        "reemettre",
        "cremer",
        "tertre",
        "cermet",
        "tete",
        "relue",
        "mutee",
        "erecteur",
        "emule",
        "crue",
        "ecuelle",
        "turelure",
        "receleur",
        "reemette",
        "cumuler",
        "ecumer",
        "telemetrer",
        "creer",
        "cerule",
        "eructer",
        "ecremee",
        "recrut",
        "erre",
        "reclure",
        "culturel",
        "ecretee",
        "recurer",
        "cretelle",
        "metrer",
        "memere",
        "cremet",
        "teterelle",
        "merl",
        "melee",
        "remette",
        "leurree",
        "tellurure",
        "ulceree",
        "crecelle",
        "remere",
        "recul",
        "meulee",
        "reculer",
        "luter",
        "telemetreur",
        "cultuel",
        "uree",
        "cule",
        "ulcerer",
        "uretere",
        "lecrelet",
        "electret",
        "crecerelle",
        "terrer",
        "recele",
        "murette",
        "ecuree",
        "cerce",
        "cruelle",
        "curure",
        "cellule",
        "tutelle",
        "meut",
        "mere",
        "culte",
        "metreur",
        "tutute",
        "mulette",
        "cure",
        "lutte",
        "cutter",
        "lecteur",
        "lemme",
        "curette",
        "truelle",
        "recel",
        "tumulte",
        "celle",
        "recuree",
        "ecumeur",
        "recu",
        "emmurer",
        "luette",
        "curer",
        "eteule",
        "reelle",
        "meurtre",
        "ecumee",
        "reemet",
        "lettree",
        "reclut",
        "ulule",
        "lurette",
        "cercle",
        "tuer",
        "erreur",
        "telemetree",
        "eculer",
        "cuculle",
        "tremule",
        "meurt",
        "cret",
        "reemetteur",
        "ecremeur",
        "etete",
        "recelee",
        "recru",
        "mule",
        "creter",
        "meure",
        "murmel",
        "remueur",
        "remeler",
        "eluee",
        "cultuelle",
        "turlute",
        "recruter",
        "muette",
        "tetee",
        "culee",
        "recut",
        "emette",
        "merlu",
        "recreer",
        "teter",
        "ulcere",
        "metteur",
        "meute",
        "meltem",
        "ruelle",
        "tuteur",
        "crete",
        "emmeler",
        "creme",
        "memerer",
        "lecture",
        "ecuellee",
        "tumeur",
        "tulle",
        "recteur",
        "creee",
        "retercee",
        "relecture",
        "remuer",
        "cruel",
        "terce",
        "recette",
        "cureter",
        "ecureur",
        "tette",
        "emet",
        "meler",
        "terre",
        "mure",
        "ecreteur",
        "cerclee",
        "recrue",
        "meurette",
        "truellee",
        "clerc",
        "remuee",
        "leurre",
        "reer",
        "leur",
        "recerclee",
        "teletel",
        "recule",
        "muer",
        "lute",
        "mutuelle",
        "recrute",
        "cumule",
        "tercet",
        "mutule",
        "ecru",
        "recercler",
        "recree",
        "ecreter",
        "recue",
        "elut",
        "receler",
        "emeut",
        "recetter",
        "recruteur",
        "emmure",
        "ecreme",
        "ecurer",
        "eructee",
        "curule",
        "merlette",
        "remue",
        "lutteur",
        "remettre",
        "ruee",
        "rectum",
        "metre",
        "tetu",
        "meuler",
        "emmetre",
        "cree",
        "muter",
        "remet",
        "lettrer",
        "emmuree",
        "telle",
        "tremulee",
        "mulet",
        "cette",
        "merule",
        "lemur",
        "tuteurer",
        "tuteuree",
        "clue",
        "remelee",
        "tele",
        "etre",
        "elue",
        "etetee",
        "mutuel",
        "curete",
        "turlutee",
        "murmurer",
        "curleur",
        "ruer",
        "eluer",
        "ecremer",
        "emmelee",
        "curee",
        "celte",
        "lueur",
        "recure",
        "emulee",
        "turluter",
        "ecume",
        "cumulet",
        "recercle",
        "cumulee",
        "reelut",
        "terree",
        "lutter",
        "lette",
        "ecrue",
        "tercer",
        "telemetre",
        "ecrete",
        "culturelle",
        "lettre",
        "reclue",
        "lemure",
        "memee",
        "mette",
        "mele",
        "mute",
        "tetue",
        "tellure",
        "eteter",
        "murmuree",
        "emue",
        "culer",
        "cerulee",
        "meule",
        "recre",
        "tuteure",
        "relut",
        "cele",
        "cercler",
        "emettre",
        "mercure",
        "leurrer",
        "lucre",
        "lettreur",
        "meulette",
        "cretee",
        "rumeur",
        "recettee",
        "reelue",
        "uretre",
        "terreur",
        "emeute",
        "retercer",
        "remele",
        "errer",
        "celee",
        "relu",
        "emmele",
        "emmetrer",
        "muret",
        "eculee",
        "tremelle",
        "tercee",
        "ecure",
        "murer",
        "curetee",
        "turlurette",
        "electrum",
        "lutee",
        "muree",
        "emetteur",
        "tueur",
        "reterce",
        "tremuler",
        "merle",
        "tell",
        "muet",
        "cutteur",
        "electeur",
        "metree",
        "tuee",
        "mettre",
        "culture",
        "relecteur",
        "ululer",
        "cureur",
        "emmetree",
        "elle",
        "reculee",
        "emeu",
        "celer",
        "cremee",
        "murmure",
        "reel",
        "eructe",
        "ecule",
        "recreee",
        "turlutte",
        "reelu",
        "recrutee",
        "muee"
    ],
    "pangrammes": [
        "electrum"
    ]
}