{
    "day": 169,
    "letters": [
        "s",
        "g",
        "c",
        "o",
        "l",
        "n"
    ],
    "center": "a",
    "max_score": 1584,
    "n_words": 294,
    "n_pangrams": 1,
    "words": [
        "assona",
        "agaca",
        "lagan",
        "anonna",
        "cossas",
        "anon",
        "lassas",
        "assonas",
        "sassas",
        "cana",
        "naan",
        "local",
        "galonnas",
        "gallos",
        "concassas",
        "nasonna",
        "alcoolo",
        "loas",
        "gallons",
        "gansas",
        "coconnas",
        "glana",
        "canonna",
        "llanos",
        "cacaos",
        "gascons",
        "nanan",
        "galagos",
        "cassons",
        "ganga",
        "scanna",
        "coassa",
        "glanas",
        "canal",
        "sacs",
        "calls",
        "nasonnas",
        "allas",
        "cals",
        "callas",
        "algal",
        "cancanons",
        "sanglons",
        "lala",
        "galgal",
        "allons",
        "gallo",
        "lagons",
        "calaos",
        "nacs",
        "nagas",
        "glacons",
        "calons",
        "nans",
        "assos",
        "lagans",
        "lanca",
        "clans",
        "gagnas",
        "saolas",
        "glaca",
        "colla",
        "naga",
        "consola",
        "coassons",
        "glas",
        "glagla",
        "alloc",
        "concassa",
        "sala",
        "slogans",
        "goal",
        "salsa",
        "canna",
        "naans",
        "glass",
        "salols",
        "galons",
        "saola",
        "anons",
        "nocas",
        "glacas",
        "sanas",
        "callons",
        "cagnas",
        "gossas",
        "assonons",
        "sana",
        "aglossas",
        "anonnons",
        "cannons",
        "consonas",
        "agacons",
        "gasconnons",
        "sonals",
        "alcoolos",
        "cancan",
        "gagna",
        "anonas",
        "sans",
        "galonna",
        "gnangnans",
        "lacons",
        "casas",
        "nanas",
        "consolas",
        "sassons",
        "gansons",
        "cocolas",
        "canons",
        "slogan",
        "sassa",
        "cacas",
        "sonna",
        "nana",
        "calos",
        "sangos",
        "galago",
        "gasconna",
        "slang",
        "slangs",
        "cassas",
        "osas",
        "clonal",
        "agas",
        "glanons",
        "cassa",
        "saloons",
        "cossa",
        "gans",
        "googlas",
        "sangs",
        "concassons",
        "galon",
        "clona",
        "annoncons",
        "galgals",
        "canon",
        "lancas",
        "salol",
        "coca",
        "canonnas",
        "sonal",
        "casons",
        "clonas",
        "colossal",
        "scannons",
        "anona",
        "cocas",
        "anal",
        "canola",
        "sonnas",
        "annonca",
        "lassons",
        "socca",
        "asana",
        "allocs",
        "annoncas",
        "gansa",
        "lagon",
        "salon",
        "agglo",
        "alla",
        "cocoonas",
        "accolas",
        "cocoona",
        "conga",
        "cancana",
        "nasal",
        "call",
        "calas",
        "alcool",
        "canassons",
        "assolons",
        "casson",
        "cognac",
        "cacao",
        "galanga",
        "cogna",
        "alcools",
        "scans",
        "sanglas",
        "saga",
        "analogons",
        "sang",
        "calao",
        "agacas",
        "galla",
        "cloacal",
        "assolas",
        "gallas",
        "clan",
        "ananas",
        "gnangnan",
        "galangas",
        "gals",
        "sanglon",
        "salsas",
        "galas",
        "gangas",
        "accolons",
        "naos",
        "cala",
        "scannas",
        "glosas",
        "classons",
        "gang",
        "canonnons",
        "gags",
        "consona",
        "calla",
        "laos",
        "goals",
        "agonal",
        "gallon",
        "glacon",
        "cognacs",
        "agglos",
        "gossa",
        "soccas",
        "collas",
        "noca",
        "sangla",
        "gagas",
        "sango",
        "classas",
        "asso",
        "annal",
        "googla",
        "anas",
        "calo",
        "saloon",
        "lassos",
        "lalala",
        "accons",
        "cassos",
        "allo",
        "salons",
        "casco",
        "canolas",
        "canasson",
        "acons",
        "analogon",
        "coconna",
        "cagna",
        "angons",
        "algol",
        "accon",
        "canas",
        "glosa",
        "algols",
        "cocola",
        "nanans",
        "gasconnas",
        "nasonnons",
        "cola",
        "aglossa",
        "cancans",
        "cognas",
        "laca",
        "colas",
        "gangs",
        "sagas",
        "casa",
        "lasso",
        "cascos",
        "salas",
        "gala",
        "olas",
        "galonnons",
        "lacs",
        "accola",
        "coassas",
        "gascon",
        "classa",
        "cannas",
        "gnagnagna",
        "scan",
        "sals",
        "caca",
        "lancon",
        "angon",
        "congas",
        "lancons",
        "asanas",
        "anonnas",
        "cancanas",
        "gaga",
        "lassa",
        "lacas",
        "assola",
        "acon",
        "clac",
        "gagnons"
    ],
    "pangrammes": [
        "glacons"
    ]
}