{
    "day": 645,
    "letters": [
        "n",
        "l",
        "s",
        "h",
        "c",
        "p"
    ],
    "center": "a",
    "max_score": 965,
    "n_words": 208,
    "n_pangrams": 1,
    "words": [
        "chans",
        "panca",
        "pacsa",
        "chan",
        "ahana",
        "lassas",
        "sassas",
        "cana",
        "naan",
        "hancha",
        "palans",
        "achala",
        "nappas",
        "placas",
        "apps",
        "hala",
        "shan",
        "calanchas",
        "nanan",
        "halas",
        "cachacas",
        "clappas",
        "scanna",
        "lapas",
        "ahan",
        "sapas",
        "chacal",
        "canal",
        "halals",
        "sacs",
        "calls",
        "allas",
        "cals",
        "callas",
        "hasch",
        "lacha",
        "clapas",
        "lala",
        "caps",
        "panas",
        "hallal",
        "pancas",
        "nacs",
        "panacha",
        "chas",
        "lachas",
        "nans",
        "lanca",
        "clans",
        "hans",
        "clash",
        "alpa",
        "splashs",
        "pacs",
        "sala",
        "pana",
        "salsa",
        "cacha",
        "canna",
        "naans",
        "plans",
        "panachas",
        "ahanas",
        "hanap",
        "sanas",
        "calancha",
        "cash",
        "sana",
        "hanaps",
        "schlass",
        "plan",
        "cancan",
        "hacha",
        "sans",
        "casas",
        "nanas",
        "scalpas",
        "hallals",
        "clappa",
        "clapa",
        "shah",
        "schnaps",
        "sassa",
        "cappas",
        "cacas",
        "nana",
        "clap",
        "cassas",
        "halls",
        "cassa",
        "sapa",
        "plancha",
        "phasa",
        "happas",
        "pansas",
        "chassa",
        "passa",
        "alpas",
        "placa",
        "scalpa",
        "lancas",
        "claps",
        "alpacas",
        "planas",
        "chassas",
        "anal",
        "pacha",
        "clashs",
        "pacsas",
        "shanas",
        "achalas",
        "shans",
        "asana",
        "alla",
        "chachachas",
        "papas",
        "cancana",
        "nasal",
        "palpas",
        "call",
        "calas",
        "pans",
        "chacals",
        "pass",
        "schahs",
        "scalps",
        "pachas",
        "hallah",
        "scans",
        "pals",
        "phasas",
        "slash",
        "chah",
        "palas",
        "clan",
        "cappa",
        "happa",
        "appas",
        "slashs",
        "ananas",
        "paca",
        "salsas",
        "capas",
        "shana",
        "chlass",
        "laps",
        "cala",
        "scannas",
        "pansa",
        "pascal",
        "calla",
        "pacas",
        "pascals",
        "plana",
        "hallahs",
        "shahs",
        "alpha",
        "alpaca",
        "classas",
        "haschs",
        "annal",
        "cashs",
        "papal",
        "cachaca",
        "anas",
        "cachas",
        "spas",
        "lalala",
        "pala",
        "nappa",
        "sappans",
        "chahs",
        "hall",
        "splash",
        "canas",
        "clashas",
        "nanans",
        "sappan",
        "passas",
        "cancans",
        "schah",
        "papa",
        "laca",
        "casa",
        "salas",
        "lacs",
        "scalp",
        "hachas",
        "ahans",
        "capa",
        "palpa",
        "palan",
        "chachacha",
        "classa",
        "cannas",
        "scan",
        "sals",
        "caca",
        "clasha",
        "hanchas",
        "lapa",
        "asanas",
        "halal",
        "cancanas",
        "lassa",
        "lacas",
        "clac",
        "planchas"
    ],
    "pangrammes": [
        "planchas"
    ]
}