{
    "day": 1246,
    "letters": [
        "v",
        "s",
        "e",
        "o",
        "r",
        "l"
    ],
    "center": "t",
    "max_score": 2105,
    "n_words": 359,
    "n_pangrams": 2,
    "words": [
        "tersee",
        "veto",
        "osteose",
        "rostres",
        "tertre",
        "trottes",
        "toss",
        "tete",
        "tolets",
        "tresse",
        "lottes",
        "otee",
        "revoltee",
        "tortorer",
        "este",
        "sotte",
        "serrettes",
        "levretter",
        "tetees",
        "torrees",
        "tolere",
        "lestes",
        "tersees",
        "tertres",
        "etetes",
        "vervets",
        "tortore",
        "levrette",
        "lestees",
        "rester",
        "stresses",
        "sosotte",
        "roselets",
        "teterelle",
        "rets",
        "tettes",
        "osteoses",
        "osts",
        "testee",
        "stele",
        "toreros",
        "tolle",
        "revote",
        "trottee",
        "levrettes",
        "osselet",
        "solette",
        "retros",
        "sterlets",
        "rooters",
        "orvet",
        "tetroses",
        "rosettes",
        "trolle",
        "velvet",
        "ressort",
        "votees",
        "volt",
        "tores",
        "leste",
        "verstes",
        "vertes",
        "teves",
        "lerot",
        "terrer",
        "test",
        "treves",
        "sellettes",
        "sterees",
        "toreees",
        "verste",
        "trotte",
        "voletes",
        "ostos",
        "volete",
        "vert",
        "rototos",
        "teles",
        "ressorts",
        "seteree",
        "tort",
        "solerets",
        "rototo",
        "verte",
        "telles",
        "trottees",
        "lettree",
        "vetes",
        "sort",
        "revetes",
        "tressee",
        "sottes",
        "ossetes",
        "tests",
        "rollot",
        "steres",
        "verts",
        "lettrees",
        "etete",
        "revete",
        "rotos",
        "volette",
        "steree",
        "stresser",
        "sterer",
        "tore",
        "tolerees",
        "tetee",
        "sterlet",
        "televersees",
        "lotos",
        "ttoro",
        "volts",
        "tels",
        "restee",
        "tres",
        "teter",
        "tosser",
        "tresor",
        "sots",
        "tets",
        "restos",
        "voleter",
        "volettes",
        "televersee",
        "teterelles",
        "vetos",
        "ttoros",
        "terse",
        "rostre",
        "tortoree",
        "votres",
        "revet",
        "volter",
        "toles",
        "ossete",
        "tortes",
        "tette",
        "televerses",
        "terre",
        "revotee",
        "volet",
        "stere",
        "sellette",
        "tolees",
        "teletel",
        "etetees",
        "osselets",
        "tolles",
        "ressortes",
        "toleres",
        "vete",
        "stressees",
        "vote",
        "rote",
        "stress",
        "velvotes",
        "retors",
        "voter",
        "tells",
        "strettes",
        "televerser",
        "rollots",
        "roselet",
        "stertor",
        "trollees",
        "totos",
        "velvets",
        "lorettes",
        "otees",
        "rotes",
        "terrestre",
        "retersees",
        "testees",
        "revolter",
        "toler",
        "lotes",
        "stertors",
        "velot",
        "velvote",
        "trole",
        "lorette",
        "tees",
        "sets",
        "televerse",
        "torves",
        "torve",
        "versets",
        "lettes",
        "esters",
        "teste",
        "estes",
        "terrestres",
        "terres",
        "ester",
        "serte",
        "lettrer",
        "treve",
        "telle",
        "verset",
        "sterol",
        "tors",
        "rotors",
        "velet",
        "sertes",
        "etole",
        "rotees",
        "terses",
        "levrettees",
        "revolte",
        "trolles",
        "serrette",
        "tele",
        "etoles",
        "stores",
        "otes",
        "etre",
        "soleret",
        "osteos",
        "stereos",
        "torees",
        "lerots",
        "etetee",
        "veltes",
        "teve",
        "sosots",
        "oter",
        "trots",
        "lotte",
        "stereo",
        "revoltees",
        "loto",
        "rotor",
        "roter",
        "orvets",
        "torrs",
        "toreer",
        "resto",
        "velets",
        "tresors",
        "torree",
        "tresser",
        "tessere",
        "rooter",
        "revotees",
        "sveltes",
        "store",
        "solettes",
        "sorts",
        "tesselle",
        "terree",
        "toto",
        "lette",
        "retro",
        "rotee",
        "trollee",
        "oestres",
        "sterols",
        "stressee",
        "torte",
        "lettre",
        "stresse",
        "troles",
        "svelte",
        "tolee",
        "etres",
        "tesseres",
        "roto",
        "retorse",
        "reste",
        "seterees",
        "sosot",
        "torts",
        "troller",
        "stot",
        "tsetses",
        "troll",
        "vets",
        "lester",
        "toleree",
        "eteter",
        "sorte",
        "lolette",
        "retorses",
        "oestre",
        "ressorte",
        "volte",
        "sert",
        "tosse",
        "trolls",
        "tolet",
        "velte",
        "terser",
        "vervet",
        "lolettes",
        "tortorees",
        "lots",
        "revets",
        "voltes",
        "veste",
        "rosette",
        "torr",
        "testes",
        "toree",
        "revotes",
        "trot",
        "reterser",
        "steles",
        "torero",
        "tsetse",
        "velots",
        "votes",
        "volets",
        "tortores",
        "tester",
        "trotter",
        "votre",
        "tetrose",
        "tole",
        "tresses",
        "lest",
        "reterses",
        "setters",
        "strette",
        "osto",
        "sosottes",
        "tell",
        "torses",
        "lests",
        "vestes",
        "setter",
        "terrees",
        "tressees",
        "etes",
        "tosses",
        "reterse",
        "torse",
        "lestee",
        "tetes",
        "restes",
        "restees",
        "tolerer",
        "stots",
        "revoter",
        "lote",
        "levrettee",
        "sveltesse",
        "retersee",
        "revoltes",
        "sveltesses",
        "toreee",
        "ressert",
        "osteo",
        "rots",
        "lettres",
        "tesselles",
        "teletels",
        "sortes",
        "votee"
    ],
    "pangrammes": [
        "revoltees",
        "revoltes"
    ]
}