{
    "day": 793,
    "letters": [
        "t",
        "l",
        "y",
        "i",
        "s",
        "a"
    ],
    "center": "g",
    "max_score": 536,
    "n_words": 96,
    "n_pangrams": 1,
    "words": [
        "glatis",
        "assagit",
        "agitais",
        "glissat",
        "glaisait",
        "gattais",
        "assagi",
        "glissas",
        "gitat",
        "assagis",
        "glissai",
        "agissais",
        "gisais",
        "gatai",
        "gita",
        "assagissait",
        "glissais",
        "algal",
        "taggais",
        "glial",
        "galgal",
        "glissa",
        "giga",
        "glas",
        "glagla",
        "taggas",
        "agitat",
        "tagal",
        "agis",
        "taggai",
        "glass",
        "gitais",
        "stalags",
        "gattat",
        "gata",
        "gaita",
        "gayal",
        "glati",
        "taigas",
        "agilitys",
        "glaisais",
        "gatas",
        "glaisat",
        "agas",
        "gais",
        "agissait",
        "saiga",
        "stalag",
        "gigas",
        "galgals",
        "agita",
        "gitait",
        "glatissais",
        "gisait",
        "gatat",
        "glatissait",
        "gattas",
        "glaisas",
        "glaisa",
        "tagga",
        "taggat",
        "gatait",
        "gatta",
        "sagittal",
        "agitait",
        "gatais",
        "gattait",
        "tags",
        "saga",
        "galla",
        "gallas",
        "saigas",
        "gitai",
        "gitas",
        "gals",
        "galas",
        "taggait",
        "gayals",
        "gags",
        "assagissais",
        "agility",
        "gagas",
        "gattai",
        "tagals",
        "agitas",
        "agit",
        "glissait",
        "gays",
        "glaisai",
        "sagas",
        "taiga",
        "gala",
        "glatit",
        "gaitas",
        "gaga",
        "agitai"
    ],
    "pangrammes": [
        "agilitys"
    ]
}