{
    "day": 514,
    "letters": [
        "z",
        "c",
        "p",
        "o",
        "e",
        "a"
    ],
    "center": "t",
    "max_score": 995,
    "n_words": 193,
    "n_pangrams": 1,
    "words": [
        "otat",
        "tope",
        "cotte",
        "tete",
        "petat",
        "cocotta",
        "capet",
        "otee",
        "tapa",
        "tapez",
        "papet",
        "accotee",
        "cocote",
        "cotta",
        "pota",
        "epatez",
        "accotez",
        "cooptee",
        "tapotat",
        "cata",
        "optez",
        "octet",
        "papote",
        "acceptee",
        "petaoctet",
        "petee",
        "taco",
        "opte",
        "coopta",
        "zetete",
        "accot",
        "cocotez",
        "cetace",
        "cooptat",
        "zozotez",
        "tapota",
        "appatat",
        "captee",
        "accotat",
        "tatat",
        "octette",
        "zezette",
        "cottee",
        "appatee",
        "cotez",
        "acetate",
        "papatte",
        "cactacee",
        "cocotte",
        "tetez",
        "etetat",
        "papette",
        "etete",
        "zapette",
        "tata",
        "topo",
        "tapotee",
        "capte",
        "cactee",
        "etoc",
        "tetee",
        "popote",
        "actez",
        "pette",
        "tapat",
        "ecotez",
        "topaze",
        "coopte",
        "cocottez",
        "cacaotee",
        "cetacee",
        "zozota",
        "topa",
        "ecota",
        "pepette",
        "tact",
        "acte",
        "potez",
        "appat",
        "capotez",
        "azota",
        "tette",
        "tapote",
        "pete",
        "apte",
        "epate",
        "pote",
        "topat",
        "topee",
        "cate",
        "epacte",
        "papotez",
        "cottez",
        "tacca",
        "cocottat",
        "papota",
        "capot",
        "teta",
        "pacte",
        "capota",
        "tapee",
        "cooptez",
        "ataca",
        "accote",
        "tacot",
        "peta",
        "otez",
        "patte",
        "opta",
        "topez",
        "octa",
        "potet",
        "cota",
        "ecotat",
        "capotat",
        "tape",
        "azotez",
        "actee",
        "taccacee",
        "pepete",
        "optat",
        "cette",
        "tacet",
        "potat",
        "epatee",
        "etape",
        "ecot",
        "capeat",
        "eteta",
        "actat",
        "epata",
        "peotte",
        "etetee",
        "captat",
        "capta",
        "cotat",
        "papotat",
        "azote",
        "zappat",
        "cottat",
        "pate",
        "toccata",
        "accota",
        "poete",
        "cotee",
        "azotate",
        "appata",
        "toto",
        "petez",
        "capote",
        "tapotez",
        "toccate",
        "cocota",
        "zozote",
        "acceptat",
        "cote",
        "atoca",
        "tatez",
        "cacaote",
        "capat",
        "accepte",
        "patate",
        "tetat",
        "azotat",
        "acceptez",
        "acta",
        "etetez",
        "patee",
        "pattee",
        "copte",
        "pataca",
        "ecote",
        "ecotee",
        "ecopat",
        "cocotat",
        "tate",
        "epatat",
        "topette",
        "appate",
        "captez",
        "zappette",
        "zeta",
        "azotee",
        "tapette",
        "etat",
        "potee",
        "accepta",
        "cazette",
        "capotee",
        "potto",
        "appatez",
        "tatee",
        "zozotat"
    ],
    "pangrammes": [
        "capotez"
    ]
}