{
    "day": 690,
    "letters": [
        "e",
        "n",
        "o",
        "b",
        "s",
        "k"
    ],
    "center": "t",
    "max_score": 1658,
    "n_words": 271,
    "n_pangrams": 5,
    "words": [
        "bete",
        "betonnees",
        "osteose",
        "beent",
        "besets",
        "toss",
        "tenonnee",
        "tete",
        "etetent",
        "sonnette",
        "bonnettes",
        "otee",
        "otent",
        "etonne",
        "este",
        "tonne",
        "sotte",
        "tonte",
        "betes",
        "tetees",
        "tesson",
        "steenbok",
        "tons",
        "tennesse",
        "entees",
        "etetes",
        "bettes",
        "entetee",
        "kotons",
        "sosotte",
        "sente",
        "boots",
        "notons",
        "teston",
        "tettes",
        "osteoses",
        "osts",
        "testee",
        "bote",
        "betee",
        "etonnent",
        "kote",
        "bottons",
        "tenonnons",
        "benets",
        "steno",
        "entete",
        "etonnons",
        "tentes",
        "beset",
        "test",
        "botte",
        "betonne",
        "boto",
        "bossent",
        "ostos",
        "betonnons",
        "stenoses",
        "testent",
        "skeets",
        "bobettes",
        "sonotones",
        "notes",
        "benet",
        "tenno",
        "bottent",
        "entes",
        "tontons",
        "sonnet",
        "tennos",
        "nenette",
        "betonnes",
        "tennesses",
        "stokes",
        "betonnee",
        "sentent",
        "bebete",
        "sottes",
        "ossetes",
        "tests",
        "knesset",
        "obtenons",
        "tenonnes",
        "sonnent",
        "boston",
        "etonnees",
        "testons",
        "stent",
        "snobent",
        "etete",
        "bostonnent",
        "sentes",
        "stents",
        "bostons",
        "seton",
        "tetee",
        "teton",
        "enostose",
        "tentee",
        "teks",
        "stenosons",
        "skeet",
        "stetsons",
        "nenettes",
        "sots",
        "notees",
        "tets",
        "boettes",
        "bonteboks",
        "entent",
        "bobet",
        "notebook",
        "notent",
        "toton",
        "boetes",
        "kotos",
        "tekee",
        "entonnees",
        "nette",
        "sonnettes",
        "koto",
        "sonnets",
        "enostoses",
        "sonotone",
        "betees",
        "ossete",
        "nenets",
        "tette",
        "boostees",
        "note",
        "etonnee",
        "bonnet",
        "booste",
        "entetees",
        "etetees",
        "teke",
        "entetons",
        "entonnons",
        "nonotes",
        "tentent",
        "kotes",
        "tente",
        "tenons",
        "entonne",
        "entee",
        "entetent",
        "steenboks",
        "totos",
        "otees",
        "bostonnes",
        "kots",
        "entons",
        "tenon",
        "notebooks",
        "nonnette",
        "testees",
        "sont",
        "bots",
        "bonnotte",
        "boostent",
        "tees",
        "sets",
        "bobette",
        "netbook",
        "tossent",
        "betonnent",
        "teste",
        "estes",
        "tonton",
        "bonte",
        "botes",
        "botos",
        "bontebok",
        "bobets",
        "kotent",
        "bossettes",
        "entonnee",
        "otes",
        "osteos",
        "stenosees",
        "tekees",
        "etetee",
        "sosots",
        "boette",
        "neotenes",
        "tossons",
        "entonnes",
        "stenos",
        "nettetes",
        "bentos",
        "tetons",
        "tenonne",
        "bonnottes",
        "stenosent",
        "knessets",
        "boot",
        "toto",
        "tentees",
        "tenonnent",
        "sentons",
        "bottee",
        "boost",
        "tenonnees",
        "notee",
        "etetons",
        "stenosee",
        "bennent",
        "beton",
        "ententes",
        "etonnes",
        "tonnons",
        "sosot",
        "stot",
        "nonnettes",
        "bostonne",
        "osent",
        "tsetses",
        "betons",
        "nonote",
        "bontes",
        "nettes",
        "stetson",
        "tosse",
        "entetes",
        "tontes",
        "tentons",
        "testes",
        "nettete",
        "bonnette",
        "bottes",
        "entonnent",
        "sent",
        "tonnent",
        "neotene",
        "bonnets",
        "boosts",
        "bostonnons",
        "entente",
        "bebetes",
        "tsetse",
        "tonnes",
        "otons",
        "tensons",
        "tetent",
        "stone",
        "tenson",
        "bento",
        "osto",
        "sosottes",
        "tessons",
        "etes",
        "kets",
        "netbooks",
        "boete",
        "tosses",
        "setons",
        "bette",
        "stones",
        "bossette",
        "boostee",
        "tetes",
        "stots",
        "bottees",
        "ente",
        "boostons",
        "nets",
        "osteo",
        "totons",
        "boostes",
        "tekes",
        "stenose"
    ],
    "pangrammes": [
        "steenbok",
        "bonteboks",
        "steenboks",
        "notebooks",
        "netbooks"
    ]
}