{
    "day": 389,
    "letters": [
        "r",
        "i",
        "t",
        "c",
        "x",
        "e"
    ],
    "center": "s",
    "max_score": 2714,
    "n_words": 421,
    "n_pangrams": 1,
    "words": [
        "tersee",
        "tierces",
        "excretees",
        "rescrits",
        "tiers",
        "cretes",
        "serti",
        "excretes",
        "secretrice",
        "crises",
        "sirs",
        "tresse",
        "criser",
        "trisectrice",
        "tics",
        "terrieres",
        "sexees",
        "ciriers",
        "cers",
        "tristesse",
        "este",
        "serrettes",
        "recitees",
        "sextettes",
        "tetees",
        "sertites",
        "ristrette",
        "iteres",
        "etirees",
        "sises",
        "eres",
        "tsitsits",
        "terris",
        "tirees",
        "tersees",
        "sesterces",
        "tertres",
        "risers",
        "ecris",
        "tisser",
        "etetes",
        "riccies",
        "ecrits",
        "exits",
        "rester",
        "serie",
        "stresses",
        "titrees",
        "cerces",
        "rets",
        "tettes",
        "testee",
        "rectrices",
        "secrets",
        "rexiste",
        "recrites",
        "retrecisse",
        "retrecis",
        "excises",
        "sertisse",
        "sericites",
        "excisees",
        "resiste",
        "esses",
        "ceste",
        "sertir",
        "cerisette",
        "recries",
        "rexistes",
        "setiers",
        "tiser",
        "cirees",
        "test",
        "ristes",
        "rits",
        "sterees",
        "scieries",
        "strictes",
        "trities",
        "sites",
        "sexe",
        "serties",
        "sereres",
        "erres",
        "riser",
        "cerise",
        "excise",
        "retrecites",
        "exercees",
        "secreter",
        "serre",
        "sexes",
        "tries",
        "irisee",
        "ecries",
        "recriees",
        "seteree",
        "tirettes",
        "tectrices",
        "stricts",
        "criticiste",
        "secrete",
        "striee",
        "exercices",
        "recreees",
        "existes",
        "risses",
        "retirees",
        "resserres",
        "tierceistes",
        "tressee",
        "sexte",
        "stricte",
        "tests",
        "reis",
        "crets",
        "cirieres",
        "steres",
        "secs",
        "ecceites",
        "sexiste",
        "iris",
        "striees",
        "creees",
        "cecites",
        "cricris",
        "criticistes",
        "steree",
        "etires",
        "stresser",
        "sterer",
        "sertit",
        "tissees",
        "sire",
        "titrise",
        "triesters",
        "serrer",
        "cessee",
        "certes",
        "ecretees",
        "tercees",
        "erses",
        "crees",
        "reiterees",
        "restee",
        "exces",
        "strict",
        "siestes",
        "tres",
        "retissees",
        "serree",
        "tetieres",
        "ceistes",
        "rires",
        "titiste",
        "sesterce",
        "retisser",
        "tets",
        "exister",
        "seriees",
        "erectrices",
        "iterees",
        "cites",
        "etrecisses",
        "terrisses",
        "siee",
        "existe",
        "sertisses",
        "criees",
        "setier",
        "tise",
        "terse",
        "resserre",
        "cesser",
        "titres",
        "crisser",
        "etrecites",
        "serere",
        "retires",
        "stere",
        "sextets",
        "cessees",
        "series",
        "etetees",
        "sectes",
        "risettes",
        "irritees",
        "ceiste",
        "stressees",
        "resserree",
        "serrees",
        "irise",
        "stress",
        "resister",
        "trieres",
        "crise",
        "excretrices",
        "crisse",
        "recrits",
        "secretes",
        "titrises",
        "siccites",
        "terces",
        "rectites",
        "tisse",
        "strettes",
        "citees",
        "sertis",
        "scie",
        "cerisiers",
        "site",
        "tisses",
        "sixtes",
        "trisectrices",
        "terrisse",
        "resistes",
        "riste",
        "sextet",
        "sires",
        "titistes",
        "cirres",
        "tristes",
        "terrestre",
        "retersees",
        "cerites",
        "testees",
        "crics",
        "secretee",
        "tristesses",
        "recettes",
        "ecrites",
        "textees",
        "sieste",
        "seriee",
        "tees",
        "sets",
        "rites",
        "serier",
        "cretees",
        "execrees",
        "seres",
        "etrecisse",
        "siester",
        "esters",
        "tirs",
        "cirses",
        "teste",
        "crisses",
        "cistes",
        "estes",
        "terrestres",
        "terres",
        "secret",
        "secretees",
        "ester",
        "titriser",
        "serte",
        "recettees",
        "textes",
        "risees",
        "titis",
        "sertes",
        "serristes",
        "terses",
        "strix",
        "tris",
        "scierie",
        "cerisier",
        "rescrit",
        "cirse",
        "trisse",
        "serrette",
        "tritiees",
        "sirex",
        "strie",
        "etriers",
        "serriste",
        "cistre",
        "sexer",
        "tercets",
        "trisser",
        "xeres",
        "sere",
        "cerisettes",
        "recres",
        "tissee",
        "sciee",
        "ixees",
        "retisse",
        "sise",
        "retrecies",
        "retercees",
        "tsitsit",
        "tresser",
        "tessere",
        "territes",
        "recrees",
        "ecretes",
        "ecriees",
        "ristrettes",
        "criteres",
        "cerises",
        "serres",
        "iritis",
        "titrisees",
        "scies",
        "ressers",
        "sistres",
        "stressee",
        "recits",
        "icteres",
        "cistres",
        "stresse",
        "criticites",
        "reecris",
        "cries",
        "strier",
        "etres",
        "tesseres",
        "trissees",
        "reste",
        "trisses",
        "terriers",
        "seterees",
        "trics",
        "execres",
        "reecrits",
        "sexistes",
        "exerces",
        "tsetses",
        "etrecis",
        "sers",
        "tires",
        "ixes",
        "irises",
        "sert",
        "risee",
        "rixes",
        "tierceiste",
        "sexee",
        "cesses",
        "terser",
        "exereses",
        "sixte",
        "secretrices",
        "tirets",
        "recris",
        "testes",
        "resserrer",
        "sixties",
        "etrecies",
        "exciser",
        "sertie",
        "cris",
        "cesse",
        "etiers",
        "reiteres",
        "excisee",
        "titrisee",
        "reterser",
        "irisees",
        "stries",
        "retissee",
        "etisies",
        "risette",
        "excites",
        "etisie",
        "reterces",
        "tsetse",
        "cestes",
        "tiercees",
        "reecrites",
        "tester",
        "esse",
        "tresses",
        "reterses",
        "triees",
        "setters",
        "ries",
        "irrites",
        "strette",
        "tises",
        "risse",
        "ires",
        "retrecisses",
        "iriser",
        "setter",
        "sextette",
        "criss",
        "sistre",
        "terrees",
        "tressees",
        "ciste",
        "retisses",
        "etes",
        "sericite",
        "exerese",
        "reitres",
        "reterse",
        "sextes",
        "siccite",
        "secte",
        "tetes",
        "rees",
        "restes",
        "restees",
        "erse",
        "trissee",
        "excitees",
        "sciees",
        "recites",
        "retersee",
        "ressert",
        "tectites",
        "riss",
        "cires",
        "resserrees",
        "scier",
        "reces",
        "triste",
        "triester"
    ],
    "pangrammes": [
        "excretrices"
    ]
}