{
    "day": 565,
    "letters": [
        "l",
        "k",
        "m",
        "e",
        "r",
        "i"
    ],
    "center": "c",
    "max_score": 583,
    "n_words": 100,
    "n_pangrams": 1,
    "words": [
        "reck",
        "cric",
        "micelle",
        "cremer",
        "cicle",
        "cirer",
        "creer",
        "ecremee",
        "ecriee",
        "recrie",
        "creek",
        "ecrire",
        "crecelle",
        "cremiere",
        "cire",
        "cellerier",
        "cilice",
        "crecerelle",
        "recele",
        "cerce",
        "celeri",
        "icelle",
        "recel",
        "celle",
        "clim",
        "reecrire",
        "milice",
        "cercle",
        "licier",
        "ecrie",
        "recelee",
        "ciriere",
        "remerciee",
        "ecrier",
        "cellier",
        "recreer",
        "lice",
        "creme",
        "crier",
        "cremerie",
        "recrire",
        "cirier",
        "cillee",
        "creee",
        "remercier",
        "recrier",
        "ciel",
        "ecimer",
        "leckerli",
        "cerclee",
        "cille",
        "clerc",
        "recerclee",
        "ciliee",
        "cicler",
        "cimier",
        "click",
        "kicker",
        "ciller",
        "ciclee",
        "recercler",
        "criee",
        "recree",
        "crie",
        "mercerie",
        "receler",
        "cellererie",
        "celleriere",
        "ecreme",
        "riccie",
        "cecilie",
        "cree",
        "ciree",
        "crime",
        "ecime",
        "ecremer",
        "remercie",
        "recercle",
        "cirre",
        "kick",
        "merciere",
        "limerick",
        "recriee",
        "cricri",
        "cremier",
        "liciere",
        "recre",
        "cele",
        "cercler",
        "mercier",
        "ecimee",
        "celee",
        "cime",
        "ceci",
        "merci",
        "cilie",
        "celer",
        "cremee",
        "recreee",
        "clic"
    ],
    "pangrammes": [
        "limerick"
    ]
}