{
    "day": 1275,
    "letters": [
        "p",
        "m",
        "u",
        "o",
        "i",
        "d"
    ],
    "center": "s",
    "max_score": 360,
    "n_words": 84,
    "n_pangrams": 2,
    "words": [
        "pioupious",
        "ouis",
        "sumo",
        "doudous",
        "pudus",
        "suppos",
        "dumdums",
        "mips",
        "sous",
        "soumis",
        "moisis",
        "dodus",
        "mous",
        "poids",
        "sois",
        "pissou",
        "soums",
        "pissous",
        "soussous",
        "omis",
        "moisi",
        "mossis",
        "dispos",
        "dops",
        "moussus",
        "dips",
        "sidi",
        "ouds",
        "popups",
        "moussu",
        "mossi",
        "usus",
        "midis",
        "sodium",
        "podiums",
        "pois",
        "issu",
        "oidiums",
        "oppidums",
        "dois",
        "mouds",
        "osmiums",
        "doums",
        "summums",
        "sipo",
        "doms",
        "siums",
        "oups",
        "opossums",
        "sium",
        "dispo",
        "miss",
        "ossu",
        "osmium",
        "misos",
        "sipos",
        "summum",
        "opossum",
        "duos",
        "miso",
        "dissous",
        "sumos",
        "opus",
        "puis",
        "sidis",
        "dodos",
        "pipos",
        "mimis",
        "muids",
        "pops",
        "duodis",
        "ossus",
        "pipis",
        "mois",
        "soms",
        "issus",
        "suppo",
        "suis",
        "opiums",
        "spis",
        "soussou",
        "soum",
        "domus",
        "sodiums"
    ],
    "pangrammes": [
        "podiums",
        "oppidums"
    ]
}