{
    "day": 1327,
    "letters": [
        "r",
        "l",
        "v",
        "a",
        "i",
        "g"
    ],
    "center": "u",
    "max_score": 315,
    "n_words": 62,
    "n_pangrams": 2,
    "words": [
        "guar",
        "larguai",
        "virgulai",
        "ragua",
        "argua",
        "vaguai",
        "guili",
        "aula",
        "grau",
        "aguillai",
        "luirai",
        "gluai",
        "guiliguili",
        "gluau",
        "gaur",
        "guai",
        "ligua",
        "irriguai",
        "glui",
        "ululai",
        "ruai",
        "ulula",
        "aguilla",
        "gruau",
        "vagua",
        "liguai",
        "giguai",
        "rugir",
        "aigu",
        "glua",
        "gaulai",
        "aiguilla",
        "rugi",
        "ruilai",
        "luira",
        "ruila",
        "lulu",
        "gigua",
        "rural",
        "rugirai",
        "augural",
        "irrigua",
        "illuvial",
        "augura",
        "aiguillai",
        "rugira",
        "guru",
        "uvula",
        "gaura",
        "uval",
        "largua",
        "aura",
        "arguai",
        "agui",
        "virgula",
        "aiguail",
        "gaula",
        "raguai",
        "augurai",
        "alluvial",
        "aurai",
        "valu"
    ],
    "pangrammes": [
        "virgulai",
        "virgula"
    ]
}