{
    "day": 213,
    "letters": [
        "n",
        "e",
        "u",
        "a",
        "t",
        "q"
    ],
    "center": "d",
    "max_score": 810,
    "n_words": 127,
    "n_pangrams": 1,
    "words": [
        "tendent",
        "detendue",
        "edente",
        "denattant",
        "detend",
        "dunette",
        "datte",
        "tauda",
        "attendu",
        "dent",
        "tendu",
        "endentant",
        "denattat",
        "dentee",
        "denudat",
        "endettee",
        "edentent",
        "eduquat",
        "endentee",
        "etendant",
        "attendue",
        "etend",
        "endettent",
        "datent",
        "attendent",
        "etendent",
        "dente",
        "endentent",
        "data",
        "denatte",
        "denuee",
        "detendu",
        "detenant",
        "eduen",
        "eden",
        "datant",
        "denattent",
        "detendent",
        "denua",
        "adnee",
        "denta",
        "duqua",
        "eduquee",
        "adequat",
        "taudent",
        "enneade",
        "etendu",
        "denuent",
        "endenta",
        "attende",
        "attend",
        "detende",
        "entende",
        "denudant",
        "eduque",
        "dentue",
        "detenue",
        "denuda",
        "endentat",
        "taudat",
        "tendant",
        "eduqua",
        "eduenne",
        "endette",
        "entendu",
        "etende",
        "dentent",
        "dette",
        "denudent",
        "dentat",
        "endettant",
        "denudee",
        "tendante",
        "adequate",
        "denuat",
        "endetta",
        "duquant",
        "endente",
        "endettat",
        "duquat",
        "edenta",
        "taude",
        "tend",
        "dentu",
        "duquee",
        "attendant",
        "edentat",
        "edentee",
        "eduquent",
        "dentant",
        "dada",
        "detendant",
        "etendue",
        "tende",
        "denue",
        "datat",
        "datee",
        "denude",
        "adent",
        "entend",
        "denatta",
        "taudee",
        "quad",
        "addenda",
        "dundee",
        "detente",
        "entendent",
        "eduquant",
        "quand",
        "taudant",
        "entendante",
        "dune",
        "entendue",
        "detenu",
        "tendue",
        "date",
        "denattee",
        "etude",
        "denuant",
        "adne",
        "andante",
        "duque",
        "edentant",
        "taud",
        "aede",
        "duquent",
        "entendant"
    ],
    "pangrammes": [
        "eduquant"
    ]
}