{
    "day": 296,
    "letters": [
        "m",
        "o",
        "f",
        "r",
        "s",
        "e"
    ],
    "center": "l",
    "max_score": 959,
    "n_words": 164,
    "n_pangrams": 6,
    "words": [
        "moflees",
        "lomo",
        "froler",
        "roles",
        "moselles",
        "felles",
        "seller",
        "mollo",
        "melos",
        "rollers",
        "ressemeler",
        "reels",
        "leser",
        "orle",
        "molosses",
        "moselle",
        "moelles",
        "merl",
        "melee",
        "felee",
        "formel",
        "melo",
        "fleole",
        "sels",
        "remeles",
        "ferles",
        "merles",
        "lesee",
        "flores",
        "moflee",
        "roseole",
        "lemme",
        "moffle",
        "merls",
        "sellees",
        "lors",
        "reelle",
        "sellee",
        "rolles",
        "mels",
        "self",
        "meles",
        "moelle",
        "ferlees",
        "molle",
        "morfle",
        "frele",
        "rolle",
        "moffler",
        "lems",
        "flemmes",
        "molosse",
        "remeler",
        "freles",
        "selles",
        "ressemelee",
        "melomele",
        "lofer",
        "floe",
        "frolee",
        "loses",
        "roseoles",
        "moffles",
        "morfler",
        "emmeler",
        "folles",
        "flemme",
        "formels",
        "formoles",
        "flore",
        "ressemelees",
        "felle",
        "meler",
        "formol",
        "mole",
        "mofflees",
        "morflee",
        "moles",
        "loess",
        "reelles",
        "lofe",
        "sols",
        "fofolle",
        "mollesse",
        "semelle",
        "mofles",
        "feler",
        "femelle",
        "orles",
        "formoler",
        "formolees",
        "formolee",
        "felees",
        "lofes",
        "fele",
        "lolo",
        "semelles",
        "lofs",
        "leses",
        "elfes",
        "olle",
        "lose",
        "morelles",
        "mofle",
        "feles",
        "remelee",
        "frole",
        "formelles",
        "emmelee",
        "morelle",
        "mofflee",
        "femelles",
        "meloes",
        "mofler",
        "emmelees",
        "remelees",
        "meloe",
        "melees",
        "lomos",
        "melomeles",
        "morflees",
        "losers",
        "mele",
        "folle",
        "molles",
        "floes",
        "role",
        "formole",
        "selfs",
        "formelle",
        "soles",
        "ferle",
        "ferlee",
        "lolos",
        "lesees",
        "remele",
        "mollesses",
        "emmele",
        "fofolles",
        "ressemelle",
        "fleoles",
        "roller",
        "elfe",
        "ressemelles",
        "selle",
        "sole",
        "frolees",
        "lese",
        "elles",
        "solo",
        "ressemeles",
        "merle",
        "formols",
        "emmeles",
        "ferler",
        "solos",
        "loser",
        "elle",
        "morfles",
        "lemmes",
        "froles",
        "rolls",
        "reel",
        "ressemele"
    ],
    "pangrammes": [
        "formels",
        "formoles",
        "formolees",
        "formelles",
        "morflees",
        "morfles"
    ]
}