{
    "day": 49,
    "letters": [
        "h",
        "a",
        "t",
        "p",
        "o",
        "n"
    ],
    "center": "r",
    "max_score": 875,
    "n_words": 142,
    "n_pangrams": 4,
    "words": [
        "rapa",
        "honora",
        "toronnat",
        "tarant",
        "tarat",
        "rapt",
        "apparat",
        "patronnat",
        "pharaon",
        "nanar",
        "rattrapant",
        "ratant",
        "proton",
        "tortora",
        "rappat",
        "ornant",
        "athanor",
        "tantra",
        "parapha",
        "tartan",
        "ratat",
        "portor",
        "apporta",
        "toron",
        "pronat",
        "parat",
        "tort",
        "rapatronna",
        "rototo",
        "prao",
        "parant",
        "raton",
        "trantran",
        "haro",
        "ttoro",
        "torah",
        "trappant",
        "ronronnat",
        "porno",
        "attrapa",
        "tronant",
        "trop",
        "trappat",
        "part",
        "trottant",
        "harpa",
        "appart",
        "tronat",
        "patronat",
        "patro",
        "honorat",
        "tarpon",
        "rapportant",
        "rapant",
        "prona",
        "ronron",
        "paraphat",
        "hart",
        "apport",
        "rapatronnant",
        "attrapant",
        "taratata",
        "pronant",
        "para",
        "phanatron",
        "parton",
        "tortorant",
        "ratonnat",
        "tarot",
        "patronnant",
        "apportant",
        "rapatronnat",
        "trapp",
        "orant",
        "torana",
        "harponnat",
        "rattrapat",
        "rohart",
        "tarpan",
        "trona",
        "ornat",
        "parano",
        "honorant",
        "rotant",
        "ronronna",
        "rotat",
        "natron",
        "taro",
        "orna",
        "rata",
        "toronna",
        "rotor",
        "tahr",
        "porta",
        "narra",
        "ponor",
        "narrat",
        "rapportat",
        "apportat",
        "harpat",
        "tara",
        "rota",
        "rapat",
        "tatar",
        "patron",
        "roto",
        "rapport",
        "harponnant",
        "partant",
        "rattrapa",
        "portat",
        "hora",
        "paraphant",
        "ratonnant",
        "ratonna",
        "rappant",
        "rappa",
        "anar",
        "arhat",
        "torr",
        "thoron",
        "trot",
        "proto",
        "patronna",
        "prorata",
        "harponna",
        "narrant",
        "port",
        "trottat",
        "thora",
        "phanotron",
        "harpon",
        "attrapat",
        "portant",
        "rapporta",
        "trotta",
        "trappa",
        "toronnant",
        "harpant",
        "ronronnant",
        "porto",
        "tortorat"
    ],
    "pangrammes": [
        "phanatron",
        "harponnat",
        "harponnant",
        "phanotron"
    ]
}